flask_routeview/__init__.py
flask_routeview-1.2.1.dist-info/LICENSE
flask_routeview-1.2.1.dist-info/METADATA
flask_routeview-1.2.1.dist-info/WHEEL
flask_routeview-1.2.1.dist-info/top_level.txt
flask_routeview-1.2.1.dist-info/RECORD
